cloud_utils/__init__.py
cloud_utils/aio_storage.py
cloud_utils/const.py
cloud_utils/exceptions.py
cloud_utils/storage.py
cloud_utils/types.py
cloud_utils/utils.py
pbx_cloud_utils-1.6.1.dist-info/METADATA
pbx_cloud_utils-1.6.1.dist-info/WHEEL
pbx_cloud_utils-1.6.1.dist-info/top_level.txt
pbx_cloud_utils-1.6.1.dist-info/RECORD
