Metadata-Version: 2.4
Name: pbx-cloud_utils
Version: 1.6.1
Summary: Cloud utilities for PBX
Project-URL: Homepage, https://getprintbox.com/
Requires-Python: >=3.11
Requires-Dist: boto3<1.36.0
Requires-Dist: aiobotocore==2.17.0
Requires-Dist: azure-storage-blob>=12.27.1
Requires-Dist: google-cloud-storage>=3.6.0
